pytorch_tabular/__init__.py
pytorch_tabular/categorical_encoders.py
pytorch_tabular/feature_extractor.py
pytorch_tabular/tabular_datamodule.py
pytorch_tabular/tabular_model.py
pytorch_tabular/tabular_model_sweep.py
pytorch_tabular/tabular_model_tuner.py
pytorch_tabular/config/__init__.py
pytorch_tabular/config/config.py
pytorch_tabular/models/__init__.py
pytorch_tabular/models/base_model.py
pytorch_tabular/models/autoint/__init__.py
pytorch_tabular/models/autoint/autoint.py
pytorch_tabular/models/autoint/config.py
pytorch_tabular/models/category_embedding/__init__.py
pytorch_tabular/models/category_embedding/category_embedding_model.py
pytorch_tabular/models/category_embedding/config.py
pytorch_tabular/models/common/__init__.py
pytorch_tabular/models/common/heads/__init__.py
pytorch_tabular/models/common/heads/blocks.py
pytorch_tabular/models/common/heads/config.py
pytorch_tabular/models/common/layers/__init__.py
pytorch_tabular/models/common/layers/activations.py
pytorch_tabular/models/common/layers/batch_norm.py
pytorch_tabular/models/common/layers/embeddings.py
pytorch_tabular/models/common/layers/gated_units.py
pytorch_tabular/models/common/layers/misc.py
pytorch_tabular/models/common/layers/soft_trees.py
pytorch_tabular/models/common/layers/transformers.py
pytorch_tabular/models/danet/__init__.py
pytorch_tabular/models/danet/arch_blocks.py
pytorch_tabular/models/danet/config.py
pytorch_tabular/models/danet/danet.py
pytorch_tabular/models/ft_transformer/__init__.py
pytorch_tabular/models/ft_transformer/config.py
pytorch_tabular/models/ft_transformer/ft_transformer.py
pytorch_tabular/models/gandalf/__init__.py
pytorch_tabular/models/gandalf/config.py
pytorch_tabular/models/gandalf/gandalf.py
pytorch_tabular/models/gate/__init__.py
pytorch_tabular/models/gate/config.py
pytorch_tabular/models/gate/gate_model.py
pytorch_tabular/models/mixture_density/__init__.py
pytorch_tabular/models/mixture_density/config.py
pytorch_tabular/models/mixture_density/mdn.py
pytorch_tabular-1.1.1.dist-info/LICENSE
pytorch_tabular-1.1.1.dist-info/METADATA
pytorch_tabular-1.1.1.dist-info/WHEEL
pytorch_tabular-1.1.1.dist-info/top_level.txt
pytorch_tabular-1.1.1.dist-info/RECORD
