Metadata-Version: 2.1
Name: pytorch-tabular
Version: 1.1.1
Summary: A standard framework for using Deep Learning for tabular data
Home-page: https://github.com/manujosephv/pytorch_tabular
Author: Manu Joseph
Author-email: manujosephv@gmail.com
License: MIT license
Keywords: pytorch,tabular,pytorch-lightning,neural network
Platform: UNKNOWN
Classifier: Development Status :: 4 - Beta
Classifier: Intended Audience :: Developers
Classifier: License :: OSI Approved :: MIT License
Classifier: Natural Language :: English
Classifier: Programming Language :: Python :: 3
Classifier: Programming Language :: Python :: 3.8
Classifier: Programming Language :: Python :: 3.9
Classifier: Programming Language :: Python :: 3.10
Requires-Python: >=3.8
Requires-Dist: torch>=1.11.0
Requires-Dist: numpy<2.0,>1.20.0
Requires-Dist: pandas>=1.1.5
Requires-Dist: scikit-learn>=1.3.0
Requires-Dist: pytorch-lightning<2.5.0,>=2.0.0
Requires-Dist: omegaconf>=2.3.0
Requires-Dist: torchmetrics<1.6.0,>=0.10.0
Requires-Dist: tensorboard!=2.5.0,>2.2.0
Requires-Dist: protobuf<5.29.0,>=3.20.0
Requires-Dist: pytorch-tabnet==4.1
Requires-Dist: PyYAML<6.1.0,>=5.4
Requires-Dist: matplotlib>3.1
Requires-Dist: ipywidgets
Requires-Dist: einops<0.8.0,>=0.6.0
Requires-Dist: rich>=11.0.0
Provides-Extra: dev
Requires-Dist: wget; extra == "dev"
Requires-Dist: bump2version==1.0.1; extra == "dev"
Requires-Dist: mkdocs-material==9.5.*; extra == "dev"
Requires-Dist: ipython[notebook]<9.0,>8.0; extra == "dev"
Requires-Dist: mkdocstrings[python]==0.26.*; extra == "dev"
Requires-Dist: mknotebooks==0.8.*; extra == "dev"
Requires-Dist: pytest>=5.3.2; extra == "dev"
Requires-Dist: pytest-runner>=5.1; extra == "dev"
Requires-Dist: torch-optimizer; extra == "dev"
Provides-Extra: extra
Requires-Dist: wandb<0.19.0,>=0.15.0; extra == "extra"
Requires-Dist: plotly<5.25.0,>=5.13.0; extra == "extra"
Requires-Dist: kaleido<0.3.0,>=0.2.0; extra == "extra"
Requires-Dist: captum<0.8.0,>=0.5.0; extra == "extra"
